mirzai/__init__.py
mirzai/_modidx.py
mirzai/data/__init__.py
mirzai/data/loading.py
mirzai/data/selection.py
mirzai/data/torch.py
mirzai/data/transform.py
mirzai/training/__init__.py
mirzai/training/cnn.py
mirzai/training/core.py
mirzai/training/metrics.py
mirzai/training/plsr.py
mirzai/vis/__init__.py
mirzai/vis/core.py
mirzai-0.4.0.dist-info/LICENSE
mirzai-0.4.0.dist-info/METADATA
mirzai-0.4.0.dist-info/WHEEL
mirzai-0.4.0.dist-info/entry_points.txt
mirzai-0.4.0.dist-info/top_level.txt
mirzai-0.4.0.dist-info/RECORD
