Metadata-Version: 2.1
Name: mirzai
Version: 0.4.0
Summary: Prediction of Exchangeable Potassium in Soil through Mid-Infrared Spectroscopy and Deep Learning: from Prediction to Explainability, Albinet et al., 2022
Home-page: https://github.com/franckalbinet/mirzai/
Author: Franck Albinet
Author-email: franckalbinet@gmail.com
License: Apache Software License 2.0
Keywords: high-throughput soil characterization remediation
Classifier: Development Status :: 3 - Alpha
Classifier: Intended Audience :: Developers
Classifier: Natural Language :: English
Classifier: Programming Language :: Python :: 3.7
Classifier: Programming Language :: Python :: 3.8
Classifier: Programming Language :: Python :: 3.9
Classifier: Programming Language :: Python :: 3.10
Classifier: License :: OSI Approved :: Apache Software License
Requires-Python: >=3.7
License-File: LICENSE
Requires-Dist: numpy
Requires-Dist: pandas
Requires-Dist: fastcore
Requires-Dist: scipy
Requires-Dist: matplotlib (>=3.5.1)
Requires-Dist: scikit-learn
Requires-Dist: torch
Requires-Dist: torchvision
Requires-Dist: tqdm
Requires-Dist: captum
Provides-Extra: dev
